README.md
setup.cfg
setup.py
awscli_plugin_tls/__init__.py
awscli_plugin_tls.egg-info/PKG-INFO
awscli_plugin_tls.egg-info/SOURCES.txt
awscli_plugin_tls.egg-info/dependency_links.txt
awscli_plugin_tls.egg-info/requires.txt
awscli_plugin_tls.egg-info/top_level.txt