Metadata-Version: 2.1
Name: awscli-plugin-tls
Version: 0.1
Summary: TLS configuration plugin for AWS CLI
Home-page: https://github.com/awslabs/awscli-plugin-tls
Author: Ryan Festag
Author-email: ryfestag@amazon.com
License: Apache License 2.0
Download-URL: https://github.com/awslabs/awscli-plugin-tls/awscli-plugin-tls-v0.1.tgz
Keywords: awscli,plugin,tls
Platform: UNKNOWN
